hcam_drivers/__init__.py
hcam_drivers/config.py
hcam_drivers/data/README.rst
hcam_drivers/data/config
hcam_drivers/data/configspec.ini
hcam_drivers/utils/__init__.py
hcam_drivers/utils/gtc.py
hcam_drivers/utils/rtplot.py
hcam_drivers/utils/web.py
hcam_drivers-1.4.1.data/scripts/compo_gui
hcam_drivers-1.4.1.data/scripts/fileserver
hcam_drivers-1.4.1.data/scripts/get_gtc_json
hcam_drivers-1.4.1.data/scripts/gtc_pointing_test
hcam_drivers-1.4.1.data/scripts/gtc_tweak_focus
hcam_drivers-1.4.1.data/scripts/gtc_tweak_pointing
hcam_drivers-1.4.1.data/scripts/hdriver
hcam_drivers-1.4.1.data/scripts/slide
hcam_drivers-1.4.1.data/scripts/slide_eng
hcam_drivers-1.4.1.data/scripts/start_hicam
hcam_drivers-1.4.1.data/scripts/stop_hicam
hcam_drivers-1.4.1.data/scripts/telemetry_gui
hcam_drivers-1.4.1.data/scripts/tsync_status
hcam_drivers-1.4.1.dist-info/AUTHORS.rst
hcam_drivers-1.4.1.dist-info/LICENSE
hcam_drivers-1.4.1.dist-info/METADATA
hcam_drivers-1.4.1.dist-info/WHEEL
hcam_drivers-1.4.1.dist-info/top_level.txt
hcam_drivers-1.4.1.dist-info/RECORD
