Metadata-Version: 2.1
Name: hcam-drivers
Version: 1.4.1
Summary: Observation planning and finding charts for HiPerCAM
Home-page: https://github.com/HiPERCAM/hcam-drivers
Download-URL: https://github.com/HiPERCAM/hcam-drivers/archive/v1.4.1.tar.gz
Author: Stuart Littlefair
Author-email: s.littlefair@shef.ac.uk
License: MIT license
Keywords: hcam-drivers
Classifier: Development Status :: 2 - Pre-Alpha
Classifier: Intended Audience :: Developers
Classifier: License :: OSI Approved :: MIT License
Classifier: Natural Language :: English
Classifier: Programming Language :: Python :: 2
Classifier: Programming Language :: Python :: 2.6
Classifier: Programming Language :: Python :: 2.7
Classifier: Programming Language :: Python :: 3
Classifier: Programming Language :: Python :: 3.3
Classifier: Programming Language :: Python :: 3.4
Classifier: Programming Language :: Python :: 3.5
License-File: LICENSE
License-File: AUTHORS.rst
Requires-Dist: astropy
Requires-Dist: autobahn
Requires-Dist: tornado
Requires-Dist: pyaml
Requires-Dist: twisted
Requires-Dist: configobj
Requires-Dist: tqdm
Requires-Dist: hcam-widgets (>=1.1.2)
Requires-Dist: hcam-devices (>=1.1.1)
Requires-Dist: pymodbus3
